nonebot_plugin_tvseries/__init__.py
nonebot_plugin_tvseries/css.css
nonebot_plugin_tvseries/date_source.py
nonebot_plugin_tvseries-0.0.2.3.dist-info/LICENSE
nonebot_plugin_tvseries-0.0.2.3.dist-info/WHEEL
nonebot_plugin_tvseries-0.0.2.3.dist-info/METADATA
nonebot_plugin_tvseries-0.0.2.3.dist-info/RECORD
