Metadata-Version: 2.1
Name: nonebot-plugin-tvseries
Version: 0.0.2.3
Summary: 
License: MIT
Author: kexue
Author-email: xana278@foxmail.com
Requires-Python: >=3.9,<4.0
Classifier: License :: OSI Approved :: MIT License
Classifier: Programming Language :: Python :: 3
Classifier: Programming Language :: Python :: 3.10
Classifier: Programming Language :: Python :: 3.9
Requires-Dist: httpx (>=0.21.3,<0.22.0)
Requires-Dist: lxml (>=4.6.4,<5.0.0)
Requires-Dist: nonebot-adapter-onebot (==2.0.0-beta.1)
Requires-Dist: nonebot-plugin-htmlrender (>=0.0.4.2,<0.0.5.0)
Requires-Dist: nonebot2 (==2.0.0-beta.1)
